LICENSE.txt
README.txt
setup.cfg
setup.py
docs/HISTORY.txt
docs/TODO.txt
docs/kprc.tmpl
examples/kpwrapper_sample.py
kpwrapper/Node_enhanced.py
kpwrapper/__init__.py
kpwrapper/discovery_enhanced.py
kpwrapper.egg-info/PKG-INFO
kpwrapper.egg-info/SOURCES.txt
kpwrapper.egg-info/dependency_links.txt
kpwrapper.egg-info/entry_points.txt
kpwrapper.egg-info/requires.txt
kpwrapper.egg-info/top_level.txt
kpwrapper.egg-info/zip-safe
test/__init__.py
test/kpwrapper_integration_test.py
test/kpwrapper_test.py