Metadata-Version: 1.0
Name: kpwrapper
Version: 1.0.4
Summary: Smart-M3 KP wrapper library
Home-page: http://asibsync.sourceforge.net
Author: Eemeli Kantola
Author-email: eemeli.kantola@iki.fi
License: BSD
Keywords: Smart-M3 SIB KP
Platform: UNKNOWN
Classifier: Intended Audience :: Developers
Classifier: Development Status :: 4 - Beta
Classifier: Programming Language :: Python :: 2.6
Classifier: Topic :: Internet
